{
    "today_picks": [
        {
            "rank": 1,
            "name": "CG인바이츠",
            "code": "083790",
            "company_summary": "[KOSDAQ]",
            "supply": "외인매수",
            "cur_price": 1320,
            "score_100": 72,
            "score": "★★★☆☆ 72점",
            "tags": "OBV60일매집 / 매매신호 / 횡보기간",
            "expected_return": "15.8%",
            "score_detail": {
                "OBV60일매집": 30,
                "매집일수": 15,
                "거래량살아있음": 15,
                "횡보기간": 20,
                "고점괴리": 10,
                "매매신호": 25,
                "거래량스파이크": 20,
                "수급강도": 8
            },
            "meta": {
                "rsi": 45.1,
                "rebound_pct": 12.7,
                "vol_ratio": 1.09,
                "inst_streak": 0,
                "for_streak": 4,
                "mktcap": 1015,
                "green_days": 56,
                "signal": 48.2,
                "max_spike": 5.6,
                "rs": -26.7,
                "trade": {
                    "entry": 1320,
                    "stop_loss": 1233,
                    "target_1": 1492,
                    "target_2": 1607,
                    "risk_pct": 6.6,
                    "reward_pct": 13.0,
                    "rr_ratio": 2.0,
                    "atr": 57.6
                },
                "rt_price_used": true,
                "spike_count": 9,
                "disp20": -2.2,
                "disp60": -3.8,
                "last_spikes": [
                    "2026-02-27",
                    "2026-03-30",
                    "2026-04-08"
                ],
                "spike_news": [],
                "sideways_days": 120,
                "high52_gap": 33.5,
                "vol_alive_ratio": 1.16,
                "obv_60_change": 189.4
            }
        },
        {
            "rank": 2,
            "name": "대보마그네틱",
            "code": "290670",
            "company_summary": "[KOSDAQ]",
            "supply": "기관매수",
            "cur_price": 12920,
            "score_100": 70,
            "score": "★★★☆☆ 70점",
            "tags": "OBV60일매집 / 거래량살아있음 / 거래량스파이크",
            "expected_return": "15.5%",
            "score_detail": {
                "OBV60일매집": 30,
                "매집일수": 15,
                "거래량살아있음": 25,
                "횡보기간": 15,
                "고점괴리": 10,
                "매매신호": 18,
                "거래량스파이크": 25,
                "수급강도": 3
            },
            "meta": {
                "rsi": 61.0,
                "rebound_pct": 29.2,
                "vol_ratio": 0.96,
                "inst_streak": 1,
                "for_streak": 0,
                "mktcap": 1015,
                "green_days": 58,
                "signal": 59.0,
                "max_spike": 10.7,
                "rs": -34.3,
                "trade": {
                    "entry": 12920,
                    "stop_loss": 11993,
                    "target_1": 14773,
                    "target_2": 16009,
                    "risk_pct": 7.2,
                    "reward_pct": 14.3,
                    "rr_ratio": 2.0,
                    "atr": 617.9
                },
                "rt_price_used": true,
                "spike_count": 7,
                "disp20": 9.9,
                "disp60": 6.1,
                "last_spikes": [
                    "2026-01-29",
                    "2026-04-02",
                    "2026-04-22"
                ],
                "spike_news": [],
                "sideways_days": 90,
                "high52_gap": 31.5,
                "vol_alive_ratio": 1.93,
                "obv_60_change": 314.99
            }
        },
        {
            "rank": 3,
            "name": "동신건설",
            "code": "025950",
            "company_summary": "[KOSDAQ]",
            "supply": "외인+기관 양매수",
            "cur_price": 17060,
            "score_100": 70,
            "score": "★★★☆☆ 70점",
            "tags": "OBV60일매집 / 매매신호 / 거래량스파이크",
            "expected_return": "15.5%",
            "score_detail": {
                "OBV60일매집": 25,
                "매집일수": 15,
                "거래량살아있음": 5,
                "횡보기간": 10,
                "고점괴리": 15,
                "매매신호": 25,
                "거래량스파이크": 25,
                "수급강도": 20
            },
            "meta": {
                "rsi": 55.3,
                "rebound_pct": 28.1,
                "vol_ratio": 0.22,
                "inst_streak": 5,
                "for_streak": 2,
                "mktcap": 1433,
                "green_days": 51,
                "signal": 54.5,
                "max_spike": 11.8,
                "rs": -37.8,
                "trade": {
                    "entry": 17060,
                    "stop_loss": 15320,
                    "target_1": 20540,
                    "target_2": 22860,
                    "risk_pct": 10.2,
                    "reward_pct": 20.4,
                    "rr_ratio": 2.0,
                    "atr": 1160.0
                },
                "rt_price_used": true,
                "spike_count": 8,
                "disp20": 3.6,
                "disp60": 2.3,
                "last_spikes": [
                    "2026-03-20",
                    "2026-04-09",
                    "2026-04-15"
                ],
                "spike_news": [],
                "sideways_days": 60,
                "high52_gap": 43.5,
                "vol_alive_ratio": 0.79,
                "obv_60_change": 35.79
            }
        },
        {
            "rank": 4,
            "name": "동국생명과학",
            "code": "303810",
            "company_summary": "[KOSDAQ]",
            "supply": "외인매수",
            "cur_price": 3545,
            "score_100": 70,
            "score": "★★★☆☆ 70점",
            "tags": "OBV60일매집 / 거래량살아있음 / 거래량스파이크",
            "expected_return": "15.5%",
            "score_detail": {
                "OBV60일매집": 30,
                "매집일수": 15,
                "거래량살아있음": 25,
                "횡보기간": 20,
                "고점괴리": 10,
                "매매신호": 10,
                "거래량스파이크": 25,
                "수급강도": 4
            },
            "meta": {
                "rsi": 57.1,
                "rebound_pct": 10.4,
                "vol_ratio": 0.37,
                "inst_streak": 0,
                "for_streak": 2,
                "mktcap": 1133,
                "green_days": 57,
                "signal": 71.0,
                "max_spike": 14.7,
                "rs": -32.7,
                "trade": {
                    "entry": 3545,
                    "stop_loss": 3411,
                    "target_1": 3812,
                    "target_2": 3991,
                    "risk_pct": 3.8,
                    "reward_pct": 7.5,
                    "rr_ratio": 2.0,
                    "atr": 89.3
                },
                "rt_price_used": true,
                "spike_count": 5,
                "disp20": 4.0,
                "disp60": 2.3,
                "last_spikes": [
                    "2026-01-29",
                    "2026-02-24",
                    "2026-04-02"
                ],
                "spike_news": [],
                "sideways_days": 120,
                "high52_gap": 33.5,
                "vol_alive_ratio": 2.35,
                "obv_60_change": 134.24
            }
        },
        {
            "rank": 5,
            "name": "이엠텍",
            "code": "091120",
            "company_summary": "[KOSDAQ]",
            "supply": "기관매수",
            "cur_price": 6730,
            "score_100": 69,
            "score": "★★★☆☆ 69점",
            "tags": "OBV60일매집 / 매매신호 / 매집일수",
            "expected_return": "15.3%",
            "score_detail": {
                "OBV60일매집": 30,
                "매집일수": 15,
                "거래량살아있음": 15,
                "횡보기간": 15,
                "고점괴리": 15,
                "매매신호": 18,
                "거래량스파이크": 15,
                "수급강도": 15
            },
            "meta": {
                "rsi": 54.0,
                "rebound_pct": 13.5,
                "vol_ratio": 2.03,
                "inst_streak": 5,
                "for_streak": 0,
                "mktcap": 1153,
                "green_days": 58,
                "signal": 65.7,
                "max_spike": 5.0,
                "rs": -49.7,
                "trade": {
                    "entry": 6730,
                    "stop_loss": 6322,
                    "target_1": 7544,
                    "target_2": 8087,
                    "risk_pct": 6.1,
                    "reward_pct": 12.1,
                    "rr_ratio": 2.0,
                    "atr": 271.4
                },
                "rt_price_used": true,
                "spike_count": 6,
                "disp20": 5.3,
                "disp60": -2.7,
                "last_spikes": [
                    "2026-02-23",
                    "2026-03-17",
                    "2026-04-27"
                ],
                "spike_news": [],
                "sideways_days": 90,
                "high52_gap": 40.4,
                "vol_alive_ratio": 1.1,
                "obv_60_change": 3746.59
            }
        }
    ],
    "scan_label": "🌙 미장 스캔",
    "total_candidates": 10,
    "total_screened": 1418,
    "filter_log": {
        "total": 1418,
        "penny": 1373,
        "mktcap": 1418,
        "bottom": 923,
        "high_gap": 223,
        "sideways": 66,
        "vol_alive": 25,
        "vol_recent": 25,
        "obv_trend": 15,
        "signal_ok": 15,
        "seforce": 14,
        "final": 10
    },
    "base_date": "20260427"
}